testpytomleexuankai/__init__.py
testpytomleexuankai/module.py
testpytomleexuankai-0.3.0.dist-info/METADATA
testpytomleexuankai-0.3.0.dist-info/WHEEL
testpytomleexuankai-0.3.0.dist-info/RECORD
