Metadata-Version: 2.1
Name: testpytomleexuankai
Version: 0.3.0
Summary: 
Author: joshua.jr
Author-email: joshua.jr@bytedance.com
Requires-Python: >=3.12,<4.0
Classifier: Programming Language :: Python :: 3
Classifier: Programming Language :: Python :: 3.12
Requires-Dist: numpy (>=2.1.0,<3.0.0)
Requires-Dist: pandas (>=2.2.2,<3.0.0)
